{
    "index": {
        "title":
            "Almost Actors",
        "slug":
            "almost-actors",
        "color":
            "#1a2d51",
        "description":
            "Almost Actors is a comedic webseries based on the terrible and often hysterical archetypes you meet in acting school, created by Tiarra Sulyk, Athena Russell, and Jessica McLeod.",
        "writtenBy":
            "Tiarra Sulyk, Athena Russell, & Jessica McLeod",
        "directedBy":
            "Various by episode",
        "starring":
            "Athena Russell, Tiarra Sulyk, Ben Groulx, Meaghan Hommy, Jessica McLeod, Cody Wilson, Robyn Westcott, Mark Anthony Parinas, Matt Mazur, Julian LeBlanc, Nicholas Carella",
        "imdb":
            "http://imdb.com/title/tt4537258/",
        "youtube":
            "https://www.youtube.com/playlist?list=PL-Kr8Im2WgzfEBV3m1T6PsQdCfL_Sug4X"
    }
}
